<?xml version='1.0' encoding='UTF-8'?>
<sch:DomainTable xmlns:sch="http://Baf.com/schemas" name="MetricType">
    <sch:name>MetricType</sch:name>
    <sch:domainType>LIST_OF_VALUES</sch:domainType>
    <sch:description></sch:description>
    <sch:domainKeys/>
    <sch:domainEntries>
        <sch:BmfDomainEntry>
            <sch:seqNumber>1</sch:seqNumber>
            <sch:displayValue>平均处理时间</sch:displayValue>
            <sch:dataValue>ResponseTimeAvg</sch:dataValue>
            <sch:keyValues>{}</sch:keyValues>
        </sch:BmfDomainEntry>
        <sch:BmfDomainEntry>
            <sch:seqNumber>2</sch:seqNumber>
            <sch:displayValue>最大处理时间</sch:displayValue>
            <sch:dataValue>ResponseTimeMax</sch:dataValue>
            <sch:keyValues>{}</sch:keyValues>
        </sch:BmfDomainEntry>
        <sch:BmfDomainEntry>
            <sch:seqNumber>3</sch:seqNumber>
            <sch:displayValue>连续失败交易数</sch:displayValue>
            <sch:dataValue>ErrorCount</sch:dataValue>
            <sch:keyValues>{}</sch:keyValues>
        </sch:BmfDomainEntry>
        <sch:BmfDomainEntry>
            <sch:seqNumber>4</sch:seqNumber>
            <sch:displayValue>交易超时</sch:displayValue>
            <sch:dataValue>Timeout</sch:dataValue>
            <sch:keyValues>{}</sch:keyValues>
        </sch:BmfDomainEntry>
        <sch:BmfDomainEntry>
            <sch:seqNumber>5</sch:seqNumber>
            <sch:displayValue>连续无交易时间</sch:displayValue>
            <sch:dataValue>IdleTime</sch:dataValue>
            <sch:keyValues>{}</sch:keyValues>
        </sch:BmfDomainEntry>
        <sch:BmfDomainEntry>
            <sch:seqNumber>6</sch:seqNumber>
            <sch:displayValue>自定义指标</sch:displayValue>
            <sch:dataValue>Custom</sch:dataValue>
            <sch:keyValues>{}</sch:keyValues>
        </sch:BmfDomainEntry>
        <sch:BmfDomainEntry>
            <sch:seqNumber>7</sch:seqNumber>
            <sch:displayValue>CPU负载</sch:displayValue>
            <sch:dataValue>CpuLoad</sch:dataValue>
            <sch:keyValues>{}</sch:keyValues>
        </sch:BmfDomainEntry>
        <sch:BmfDomainEntry>
            <sch:seqNumber>8</sch:seqNumber>
            <sch:displayValue>内存使用率</sch:displayValue>
            <sch:dataValue>RamUsage</sch:dataValue>
            <sch:keyValues>{}</sch:keyValues>
        </sch:BmfDomainEntry>
    </sch:domainEntries>
</sch:DomainTable>